WangdaoKaoyanCaozuoxitongZhishidianZhengli/README.md
WangdaoKaoyanCaozuoxitongZhishidianZhengli/__init__.py
WangdaoKaoyanCaozuoxitongZhishidianZhengli/__main__.py
WangdaoKaoyanCaozuoxitongZhishidianZhengli/file.epub
WangdaoKaoyanCaozuoxitongZhishidianZhengli/index.html
WangdaoKaoyanCaozuoxitongZhishidianZhengli/css/__init__.py
WangdaoKaoyanCaozuoxitongZhishidianZhengli/css/annotations.css
WangdaoKaoyanCaozuoxitongZhishidianZhengli/css/main.css
WangdaoKaoyanCaozuoxitongZhishidianZhengli/css/normalize.css
WangdaoKaoyanCaozuoxitongZhishidianZhengli/css/popup.css
WangdaoKaoyanCaozuoxitongZhishidianZhengli/font/__init__.py
WangdaoKaoyanCaozuoxitongZhishidianZhengli/font/fontello.eot
WangdaoKaoyanCaozuoxitongZhishidianZhengli/font/fontello.svg
WangdaoKaoyanCaozuoxitongZhishidianZhengli/font/fontello.ttf
WangdaoKaoyanCaozuoxitongZhishidianZhengli/font/fontello.woff
WangdaoKaoyanCaozuoxitongZhishidianZhengli/img/__init__.py
WangdaoKaoyanCaozuoxitongZhishidianZhengli/img/annotator-glyph-sprite.png
WangdaoKaoyanCaozuoxitongZhishidianZhengli/img/annotator-icon-sprite.png
WangdaoKaoyanCaozuoxitongZhishidianZhengli/img/apple-touch-icon.png
WangdaoKaoyanCaozuoxitongZhishidianZhengli/img/cancelfullscreen.png
WangdaoKaoyanCaozuoxitongZhishidianZhengli/img/close.png
WangdaoKaoyanCaozuoxitongZhishidianZhengli/img/fullscreen.png
WangdaoKaoyanCaozuoxitongZhishidianZhengli/img/loader.gif
WangdaoKaoyanCaozuoxitongZhishidianZhengli/img/menu-icon.png
WangdaoKaoyanCaozuoxitongZhishidianZhengli/img/save.png
WangdaoKaoyanCaozuoxitongZhishidianZhengli/img/saved.png
WangdaoKaoyanCaozuoxitongZhishidianZhengli/img/settings-s.png
WangdaoKaoyanCaozuoxitongZhishidianZhengli/img/settings.png
WangdaoKaoyanCaozuoxitongZhishidianZhengli/img/star.png
WangdaoKaoyanCaozuoxitongZhishidianZhengli/js/__init__.py
WangdaoKaoyanCaozuoxitongZhishidianZhengli/js/epub.js
WangdaoKaoyanCaozuoxitongZhishidianZhengli/js/epub.min.js
WangdaoKaoyanCaozuoxitongZhishidianZhengli/js/epub.min.map
wangdao_kaoyan_caozuoxitong_zhishidian_zhengli-2024.2.29.0.dist-info/METADATA
wangdao_kaoyan_caozuoxitong_zhishidian_zhengli-2024.2.29.0.dist-info/WHEEL
wangdao_kaoyan_caozuoxitong_zhishidian_zhengli-2024.2.29.0.dist-info/entry_points.txt
wangdao_kaoyan_caozuoxitong_zhishidian_zhengli-2024.2.29.0.dist-info/top_level.txt
wangdao_kaoyan_caozuoxitong_zhishidian_zhengli-2024.2.29.0.dist-info/RECORD
